{
  "options": {
    "children": [
      {
        "options": {
          "title": "Entity with two columns",
          "children": [
            {
              "options": {
                "children": [
                  {
                    "options": {
                      "contentType": "default",
                      "label": "First name",
                      "rightIcon": "person",
                      "value": "John"
                    },
                    "type": "component.entity-field"
                  },
                  {
                    "options": {
                      "contentType": "default",
                      "label": "Last name",
                      "rightIcon": "person",
                      "value": "Doe"
                    },
                    "type": "component.entity-field"
                  }
                ]
              },
              "type": "component.field-row"
            },
            {
              "options": {
                "children": [
                  {
                    "options": {
                      "contentType": "checkbox",
                      "label": "Checkbox",
                      "value": false
                    },
                    "type": "component.entity-field"
                  },
                  {
                    "options": {
                      "contentType": "checkbox",
                      "label": "Checkbox",
                      "value": true
                    },
                    "type": "component.entity-field"
                  }
                ]
              },
              "type": "component.field-row"
            },
            {
              "options": {
                "children": [
                  {
                    "options": {
                      "contentType": "date",
                      "label": "Date",
                      "rightIcon": "calendar",
                      "value": "=\\$fromMillis(\\$toMillis(\\$now()), '[M01]/[D01]/[Y0001]')"
                    },
                    "type": "component.entity-field"
                  },
                  {
                    "options": {
                      "contentType": "time",
                      "label": "Time",
                      "rightIcon": "time-clock-circle",
                      "value": "=\\$fromMillis(\\$toMillis(\\$now()), '[h#1]:[m01][P]')"
                    },
                    "type": "component.entity-field"
                  }
                ]
              },
              "type": "component.field-row"
            }
          ]
        },
        "type": "component.section"
      },
      {
        "options": {
          "title": "Entity styles",
          "children": [
            {
              "options": {
                "label": "Style",
                "rightIcon": "check-circle-1",
                "style": {
                  "isPositive": true
                },
                "value": "isPositive"
              },
              "type": "component.entity-field"
            },
            {
              "options": {
                "label": "Style",
                "rightIcon": "alert-circle",
                "style": {
                  "isWarning": true
                },
                "value": "isWarning"
              },
              "type": "component.entity-field"
            },
            {
              "options": {
                "label": "Style",
                "rightIcon": "alert-triangle",
                "style": {
                  "isNegative": true
                },
                "value": "isNegative"
              },
              "type": "component.entity-field"
            }
          ]
        },
        "type": "component.section"
      },
      {
        "options": {
          "title": "Interactive entity",
          "children": [
            {
              "options": {
                "contentType": "copy",
                "label": "Copy",
                "value": "Copy me!"
              },
              "type": "component.entity-field"
            },
            {
              "options": {
                "contentType": "phone",
                "label": "Phone",
                "rightIcon": "phone",
                "value": "+987 654 321"
              },
              "type": "component.entity-field"
            },
            {
              "options": {
                "contentType": "email",
                "label": "Email",
                "rightIcon": "email",
                "value": "example@jigx.com"
              },
              "type": "component.entity-field"
            },
            {
              "options": {
                "contentType": "link",
                "label": "Link",
                "rightIcon": "google",
                "value": "https://docs.jigx.com"
              },
              "type": "component.entity-field"
            }
          ]
        },
        "type": "component.section"
      },
      {
        "options": {
          "title": "Other Entities",
          "children": [
            {
              "options": {
                "contentType": "signature",
                "label": "Signature",
                "value": "https://t14345253.p.clickup-attachments.com/t14345253/c4fc68bc-8231-47b4-8fb7-60eb671fca0e/signature.png?view=open"
              },
              "type": "component.entity-field"
            },
            {
              "options": {
                "contentType": "default",
                "isMultiline": true,
                "label": "Multiline",
                "value": "Lorem ipsum dolor sit amet, putent viderer pericula per ex, cu ius sonet referrentur. Cu pri ubique mediocrem maluisset, eum ea assum vivendum constituto. Fierent accusata nec ut, ullum impetus omittam cu per. Perpetua consectetuer no ius."
              },
              "type": "component.entity-field"
            }
          ]
        },
        "type": "component.section"
      }
    ]
  },
  "type": "component.entity"
}
